{"id":"MeowBot233","profileUrl":"${path}/photos/profile.png","info":[["Alias","MeowBot233, YukisawaNya"],["Born","2003-04-15"]],"websites":[["twitter","https://twitter.com/MeowBot233"],["mastodon","https://web.archive.org/web/20240221020628/https://nekoland.fangluo.top/@fangluo"],["iconify:ri:threads-line","https://www.threads.net/@meowbot233"],["github","https://github.com/MeowBot233"],["iconify:ri:netease-cloud-music-line","https://music.163.com/#/user?id=258572198"],["Bilibili","https://space.bilibili.com/3286357"],["blog","https://fangluo.top/"]],"name":"Fangluo","comments":[{"id":17103,"content":"“但是我设立这个服务器的初衷，是希望建立一个属于大家的世界，一个超越现实让我们相遇的世界，一个更有真实感的世界。\n因此这些核心规则将永远也不会改变。”\n您走好，我们会记得...\n别的话之前明信片里跟您说过了，那就，不放在这里了。\n早上好，最后的英雄\n早上好，向你还有和你一样的人问候","submitter":"MinceraftUCST","date":"Apr 7, 2024"},{"id":17106,"content":"谢谢……\n辛苦了，我的朋友。","submitter":"Anonymous","date":"Apr 8, 2024"}]}