{"id":"hakureico","profileUrl":"${path}/photos/profile.png","info":[["昵称","千歌, Hanasaka, Hakureico"],["地区","辽宁大连"],["出生","1999-01-13"],["逝世","2018-08-09"],["年龄",19]],"websites":[["twitter","https://twitter.com/LNNU_Hakureico"],["zhihu","https://www.zhihu.com/people/hakureico"],["github","https://github.com/nekoparainfo"],["Bilibili","https://space.bilibili.com/282031569"]],"name":"神楽坂千歌","comments":[{"id":17204,"content":"千歌小天使晚安，\n渺小的星座也是闪闪发光的恒星呢……","submitter":"Anonymous","date":"Jun 5, 2024"}]}